AUTHORS
COPYING
ChangeLog
MANIFEST.in
README
gflags.py
gflags2man.py
gflags_helpxml_test.py
gflags_unittest.py
setup.py
test_module_bar.py
test_module_foo.py
debian/README
debian/changelog
debian/compat
debian/control
debian/copyright
debian/docs
debian/rules
python_gflags.egg-info/PKG-INFO
python_gflags.egg-info/SOURCES.txt
python_gflags.egg-info/dependency_links.txt
python_gflags.egg-info/top_level.txt