Metadata-Version: 1.0
Name: python-gflags
Version: 1.4
Summary: Google Commandline Flags Module
Home-page: http://code.google.com/p/python-gflags
Author: Google Inc.
Author-email: opensource@google.com
License: BSD
Platform: UNKNOWN
